{"activeAlerts":[{"alertId":62621,"status":"read","type":"commitCommentLength","created":1567189884,"alertData":{"collectionId":81657,"projectId":16076}},{"alertId":62622,"status":"new","type":"commitCommentLength","created":1567189884,"alertData":{"collectionId":81657,"projectId":16076}},{"alertId":62623,"status":"new","type":"commitCommentLength","created":1567189884,"alertData":{"collectionId":81657,"projectId":16076}},{"alertId":62624,"status":"new","type":"commitCommentLength","created":1567189884,"alertData":{"collectionId":81657,"projectId":16076}},{"alertId":62625,"status":"read","type":"commitCommentLength","created":1567189884,"alertData":{"collectionId":81657,"projectId":16076}},{"alertId":62626,"status":"read","type":"commitCommentLength","created":1567189884,"alertData":{"collectionId":81657,"projectId":16076}},{"alertId":62627,"status":"read","type":"commitCommentLength","created":1567189884,"alertData":{"collectionId":81657,"projectId":16076}},{"alertId":62628,"status":"read","type":"commitCommentLength","created":1567189884,"alertData":{"collectionId":81657,"projectId":16076}},{"alertId":62629,"status":"new","type":"rapidCommit","created":1567189884,"alertData":{"collectionId":81657,"projectId":16076}},{"alertId":62630,"status":"new","type":"rapidCommit","created":1567189884,"alertData":{"collectionId":81657,"projectId":16076}},{"alertId":62631,"status":"new","type":"rapidCommit","created":1567189884,"alertData":{"collectionId":81657,"projectId":16076}},{"alertId":62632,"status":"read","type":"rapidCommit","created":1567189884,"alertData":{"collectionId":81657,"projectId":16076}},{"alertId":62633,"status":"read","type":"rapidCommit","created":1567189884,"alertData":{"collectionId":81657,"projectId":16076}},{"alertId":62634,"status":"read","type":"rapidCommit","created":1567189884,"alertData":{"collectionId":81657,"projectId":16076}},{"alertId":62635,"status":"new","type":"rapidCommit","created":1567189884,"alertData":{"collectionId":81657,"projectId":16076}},{"alertId":62636,"status":"new","type":"rapidCommit","created":1567189884,"alertData":{"collectionId":81657,"projectId":16076}},{"alertId":62637,"status":"read","type":"rapidCommit","created":1567189884,"alertData":{"collectionId":81657,"projectId":16076}},{"alertId":62638,"status":"read","type":"rapidCommit","created":1567189884,"alertData":{"collectionId":81657,"projectId":16076}},{"alertId":62639,"status":"new","type":"rapidCommit","created":1567189884,"alertData":{"collectionId":81657,"projectId":16076}},{"alertId":62641,"status":"new","type":"commitCommentLength","created":1567189884,"alertData":{"collectionId":81724,"projectId":15988}},{"alertId":62642,"status":"new","type":"rapidCommit","created":1567189884,"alertData":{"collectionId":81724,"projectId":15988}},{"alertId":62645,"status":"new","type":"commitCommentLength","created":1567189884,"alertData":{"collectionId":81622,"projectId":15983}},{"alertId":62646,"status":"new","type":"commitCommentLength","created":1567189884,"alertData":{"collectionId":81622,"projectId":15983}},{"alertId":62647,"status":"new","type":"rapidCommit","created":1567189884,"alertData":{"collectionId":81622,"projectId":15983}},{"alertId":62648,"status":"new","type":"rapidCommit","created":1567189884,"alertData":{"collectionId":81622,"projectId":15983}},{"alertId":62653,"status":"new","type":"commitCommentLength","created":1567189884,"alertData":{"collectionId":81622,"projectId":15983}},{"alertId":62654,"status":"new","type":"commitCommentLength","created":1567189884,"alertData":{"collectionId":81622,"projectId":15983}},{"alertId":62655,"status":"read","type":"commitCommentLength","created":1567189884,"alertData":{"collectionId":81622,"projectId":15983}},{"alertId":62656,"status":"read","type":"commitCommentLength","created":1567189884,"alertData":{"collectionId":81622,"projectId":15983}},{"alertId":62620,"status":"new","type":"commitCommentLength","created":1567189884,"alertData":{"collectionId":81657,"projectId":16076}}]}
