{"247":[{"month":"2017-10","metrics":{"bce":6710.6,"avg_bce":0.44},"totalDevelopers":1183},{"month":"2017-11","metrics":{"bce":5189.55,"avg_bce":0.61},"totalDevelopers":685},{"month":"2017-12","metrics":{"bce":3871.51,"avg_bce":1.09},"totalDevelopers":489},{"month":"2019-08","metrics":{"bce":517.66,"avg_bce":3.83},"totalDevelopers":95},{"month":"2019-09","metrics":{"bce":1187.74,"avg_bce":3.16},"totalDevelopers":94}],"248":[{"month":"2017-10","metrics":{"bce":288.39,"avg_bce":1.86},"totalDevelopers":20},{"month":"2017-11","metrics":{"bce":0.0,"avg_bce":0.0},"totalDevelopers":2},{"month":"2017-12","metrics":{"bce":9.93,"avg_bce":0.71},"totalDevelopers":2}],"251":[{"month":"2017-10","metrics":{"bce":7054.88,"avg_bce":0.63},"totalDevelopers":941},{"month":"2017-11","metrics":{"bce":3985.81,"avg_bce":0.68},"totalDevelopers":477},{"month":"2017-12","metrics":{"bce":2580.17,"avg_bce":1.1},"totalDevelopers":243}],"252":[{"month":"2017-10","metrics":{"bce":1110.72,"avg_bce":0.54},"totalDevelopers":152},{"month":"2017-11","metrics":{"bce":488.38,"avg_bce":0.35},"totalDevelopers":91},{"month":"2017-12","metrics":{"bce":997.4,"avg_bce":1.26},"totalDevelopers":69}]}
